<XtraSerializer version="1.0" application="View">
  <property name="#LayoutVersion" />
  <property name="#LayoutScaleFactor">@1,Width=1@1,Height=1</property>
  <property name="OptionsBehavior" isnull="true" iskey="true">
    <property name="AllowPartialGroups">True</property>
    <property name="AlignGroupSummaryInGroupRow">True</property>
    <property name="AllowFixedGroups">True</property>
    <property name="AutoExpandAllGroups">true</property>
    <property name="AllowGroupExpandAnimation">True</property>
  </property>
  <property name="OptionsCustomization" isnull="true" iskey="true">
    <property name="AllowMergedGrouping">True</property>
  </property>
  <property name="OptionsSelection" isnull="true" iskey="true">
    <property name="ShowCheckBoxSelectorInGroupRow">True</property>
  </property>
  <property name="OptionsView" isnull="true" iskey="true">
    <property name="GroupDrawMode">Standard</property>
    <property name="ShowChildrenInGroupPanel">true</property>
    <property name="ShowAutoFilterRow">true</property>
    <property name="ShowFooter">true</property>
    <property name="ShowGroupedColumns">true</property>
    <property name="ShowGroupPanelColumnsAsSingleRow">true</property>
  </property>
  <property name="OptionsFilter" isnull="true" iskey="true">
    <property name="AllowAutoFilterConditionChange">True</property>
    <property name="FilterEditorUseMenuForOperandsAndOperators">true</property>
    <property name="DefaultFilterEditorView">VisualAndText</property>
    <property name="ShowAllTableValuesInFilterPopup">true</property>
    <property name="UseNewCustomFilterDialog">true</property>
    <property name="ShowCustomFunctions">True</property>
  </property>
  <property name="OptionsFind" isnull="true" iskey="true">
    <property name="SearchInPreview">true</property>
    <property name="AlwaysVisible">true</property>
  </property>
  <property name="OptionsMenu" isnull="true" iskey="true">
    <property name="ShowGroupSummaryEditorItem">true</property>
    <property name="ShowAddNewSummaryItem">True</property>
    <property name="ShowConditionalFormattingItem">true</property>
    <property name="EnableGroupRowMenu">true</property>
  </property>
  <property name="FixedLineWidth">2</property>
  <property name="IndicatorWidth">-1</property>
  <property name="ColumnPanelRowHeight">-1</property>
  <property name="RowSeparatorHeight">0</property>
  <property name="FooterPanelHeight">-1</property>
  <property name="HorzScrollVisibility">Auto</property>
  <property name="VertScrollVisibility">Auto</property>
  <property name="RowHeight">-1</property>
  <property name="GroupRowHeight">-1</property>
  <property name="GroupFormat">{0}: [#image]{1} {2}</property>
  <property name="ChildGridLevelName" />
  <property name="VertScrollTipFieldName" />
  <property name="PreviewFieldName" />
  <property name="GroupPanelText" />
  <property name="NewItemRowText" />
  <property name="LevelIndent">-1</property>
  <property name="PreviewIndent">-1</property>
  <property name="PreviewLineCount">-1</property>
  <property name="ScrollStyle">LiveVertScroll, LiveHorzScroll</property>
  <property name="FocusRectStyle">CellFocus</property>
  <property name="HorzScrollStep">0</property>
  <property name="OptionsClipboard" isnull="true" iskey="true">
    <property name="AllowTxtFormat">True</property>
    <property name="AllowRtfFormat">True</property>
    <property name="AllowHtmlFormat">True</property>
    <property name="AllowExcelFormat">True</property>
  </property>
  <property name="ActiveFilterEnabled">true</property>
  <property name="ViewCaptionHeight">-1</property>
  <property name="Columns" iskey="true" value="8">
    <property name="Item1" isnull="true" iskey="true">
      <property name="Name">colguid_store_bill_2</property>
      <property name="ImageAlignment">Near</property>
      <property name="ImageIndex">-1</property>
      <property name="FieldName">guid_store_bill_2</property>
      <property name="ColumnEditName" />
      <property name="Width">75</property>
      <property name="MinWidth">20</property>
      <property name="MaxWidth">0</property>
    </property>
    <property name="Item2" isnull="true" iskey="true">
      <property name="Name">colname_store</property>
      <property name="Caption">المستودع</property>
      <property name="ImageAlignment">Near</property>
      <property name="ImageIndex">-1</property>
      <property name="FieldName">name_store</property>
      <property name="ColumnEditName" />
      <property name="VisibleIndex">0</property>
      <property name="Visible">true</property>
      <property name="Width">75</property>
      <property name="MinWidth">20</property>
      <property name="MaxWidth">0</property>
    </property>
    <property name="Item3" isnull="true" iskey="true">
      <property name="Name">colQtyIN</property>
      <property name="Caption">كمية الداحل</property>
      <property name="ImageAlignment">Near</property>
      <property name="ImageIndex">-1</property>
      <property name="FieldName">QtyIN</property>
      <property name="ColumnEditName" />
      <property name="VisibleIndex">1</property>
      <property name="Visible">true</property>
      <property name="Width">75</property>
      <property name="MinWidth">20</property>
      <property name="MaxWidth">0</property>
      <property name="Summary" iskey="true" value="1">
        <property name="Item1" isnull="true" iskey="true">
          <property name="Tag" isnull="true" />
          <property name="FieldName">QtyIN</property>
          <property name="SummaryType">Sum</property>
          <property name="DisplayFormat">SUM={0:0.##}</property>
        </property>
      </property>
    </property>
    <property name="Item4" isnull="true" iskey="true">
      <property name="Name">coltotalQtyIN</property>
      <property name="Caption">قيمة الداخل</property>
      <property name="ImageAlignment">Near</property>
      <property name="ImageIndex">-1</property>
      <property name="FieldName">totalQtyIN</property>
      <property name="ColumnEditName" />
      <property name="VisibleIndex">2</property>
      <property name="Visible">true</property>
      <property name="Width">75</property>
      <property name="MinWidth">20</property>
      <property name="MaxWidth">0</property>
      <property name="Summary" iskey="true" value="1">
        <property name="Item1" isnull="true" iskey="true">
          <property name="Tag" isnull="true" />
          <property name="FieldName">totalQtyIN</property>
          <property name="SummaryType">Sum</property>
          <property name="DisplayFormat">SUM={0:0.##}</property>
        </property>
      </property>
    </property>
    <property name="Item5" isnull="true" iskey="true">
      <property name="Name">colQtyOut</property>
      <property name="Caption">كمية الخارج</property>
      <property name="ImageAlignment">Near</property>
      <property name="ImageIndex">-1</property>
      <property name="FieldName">QtyOut</property>
      <property name="ColumnEditName" />
      <property name="VisibleIndex">3</property>
      <property name="Visible">true</property>
      <property name="Width">75</property>
      <property name="MinWidth">20</property>
      <property name="MaxWidth">0</property>
      <property name="Summary" iskey="true" value="1">
        <property name="Item1" isnull="true" iskey="true">
          <property name="Tag" isnull="true" />
          <property name="FieldName">QtyOut</property>
          <property name="SummaryType">Sum</property>
          <property name="DisplayFormat">SUM={0:0.##}</property>
        </property>
      </property>
    </property>
    <property name="Item6" isnull="true" iskey="true">
      <property name="Name">coltotalQtyOut</property>
      <property name="Caption">قيمة الخارج</property>
      <property name="ImageAlignment">Near</property>
      <property name="ImageIndex">-1</property>
      <property name="FieldName">totalQtyOut</property>
      <property name="ColumnEditName" />
      <property name="VisibleIndex">4</property>
      <property name="Visible">true</property>
      <property name="Width">75</property>
      <property name="MinWidth">20</property>
      <property name="MaxWidth">0</property>
      <property name="Summary" iskey="true" value="1">
        <property name="Item1" isnull="true" iskey="true">
          <property name="Tag" isnull="true" />
          <property name="FieldName">totalQtyOut</property>
          <property name="SummaryType">Sum</property>
          <property name="DisplayFormat">SUM={0:0.##}</property>
        </property>
      </property>
    </property>
    <property name="Item7" isnull="true" iskey="true">
      <property name="Name">colQtybalance</property>
      <property name="Caption">كمية الرصيد</property>
      <property name="ImageAlignment">Near</property>
      <property name="ImageIndex">-1</property>
      <property name="FieldName">Qtybalance</property>
      <property name="ColumnEditName" />
      <property name="VisibleIndex">5</property>
      <property name="Visible">true</property>
      <property name="Width">75</property>
      <property name="MinWidth">20</property>
      <property name="MaxWidth">0</property>
      <property name="Summary" iskey="true" value="1">
        <property name="Item1" isnull="true" iskey="true">
          <property name="Tag" isnull="true" />
          <property name="FieldName">Qtybalance</property>
          <property name="SummaryType">Sum</property>
          <property name="DisplayFormat">SUM={0:0.##}</property>
        </property>
      </property>
    </property>
    <property name="Item8" isnull="true" iskey="true">
      <property name="Name">coltotalbalance</property>
      <property name="Caption">قيمة الرصيد</property>
      <property name="ImageAlignment">Near</property>
      <property name="ImageIndex">-1</property>
      <property name="FieldName">totalbalance</property>
      <property name="ColumnEditName" />
      <property name="VisibleIndex">6</property>
      <property name="Visible">true</property>
      <property name="Width">75</property>
      <property name="MinWidth">20</property>
      <property name="MaxWidth">0</property>
      <property name="Summary" iskey="true" value="1">
        <property name="Item1" isnull="true" iskey="true">
          <property name="Tag" isnull="true" />
          <property name="FieldName">totalbalance</property>
          <property name="SummaryType">Sum</property>
          <property name="DisplayFormat">SUM={0:0.##}</property>
        </property>
      </property>
    </property>
  </property>
  <property name="ViewCaption" />
  <property name="BorderStyle">Default</property>
  <property name="SynchronizeClones">true</property>
  <property name="DetailTabHeaderLocation">Top</property>
  <property name="Name">gridView1</property>
  <property name="DetailHeight">350</property>
  <property name="Tag" isnull="true" />
  <property name="GroupSummary" iskey="true" value="1">
    <property name="Item1" isnull="true" iskey="true">
      <property name="ShowInGroupColumnFooterName" />
      <property name="Tag" isnull="true" />
      <property name="FieldName">number_day1</property>
      <property name="SummaryType">None</property>
      <property name="DisplayFormat" />
    </property>
  </property>
  <property name="ActiveFilterString" />
  <property name="FormatRules" iskey="true" value="0" />
  <property name="FormatConditions" iskey="true" value="0" />
  <property name="GroupSummarySortInfoState" />
  <property name="FindFilterText" />
  <property name="FindPanelVisible">false</property>
</XtraSerializer>